gitlab_clone_mcp_server/__init__.py
gitlab_clone_mcp_server/server.py
gitlab_clone_mcp_server-1.1.0.dist-info/METADATA
gitlab_clone_mcp_server-1.1.0.dist-info/WHEEL
gitlab_clone_mcp_server-1.1.0.dist-info/entry_points.txt
gitlab_clone_mcp_server-1.1.0.dist-info/licenses/LICENCE
gitlab_clone_mcp_server-1.1.0.dist-info/RECORD
