Metadata-Version: 2.4
Name: gitlab-clone-mcp-server
Version: 1.1.0
Summary: Model Context Protocol server for GitLab API integration
Project-URL: Homepage, https://github.com/skmprb/gitlab-clone-mcp-server
Project-URL: Repository, https://github.com/skmprb/gitlab-clone-mcp-server
Project-URL: Issues, https://github.com/skmprb/gitlab-clone-mcp-server/issues
Author-email: GitLab MCP <gitlab-mcp@example.com>
License: MIT
License-File: LICENCE
Keywords: api,gitlab,mcp,server
Classifier: Development Status :: 4 - Beta
Classifier: Intended Audience :: Developers
Classifier: License :: OSI Approved :: MIT License
Classifier: Programming Language :: Python :: 3
Classifier: Programming Language :: Python :: 3.10
Classifier: Programming Language :: Python :: 3.11
Classifier: Programming Language :: Python :: 3.12
Requires-Python: >=3.10
Requires-Dist: httpx>=0.25.0
Requires-Dist: mcp[cli]>=1.12.1
Requires-Dist: starlette>=0.37.0
Requires-Dist: uvicorn>=0.24.0
